gopapi
