Metadata-Version: 1.0
Name: gopapi
Version: 1.2.1
Summary: Simple way to access GoDaddy API
Home-page: https://github.com/gamikun/gopapi
Author: Gamaliel Espinoza M.
Author-email: gamaliel.espinoza@gmail.com
License: UNKNOWN
Keywords: image,icons,
Platform: UNKNOWN
